pyjce/__init__.py
pyjce/__main__.py
pyjce/buffer.py
pyjce/head.py
pyjce/jcetypes.py
pyjce/py.typed
pyjce/reader.py
pyjce/struct.py
pyjce/typing.py
pyjce/writer.py
pyjce2-0.1.3.dist-info/LICENSE
pyjce2-0.1.3.dist-info/METADATA
pyjce2-0.1.3.dist-info/WHEEL
pyjce2-0.1.3.dist-info/top_level.txt
pyjce2-0.1.3.dist-info/RECORD
