Metadata-Version: 2.1
Name: pyjce2
Version: 0.1.3
Summary: Tencent JCE parser for Python,implement with pydantic
Home-page: https://github.com/synodriver/pyjce
Author: synodriver
Author-email: diguohuangjiajinweijun@gmail.com
Maintainer: synodriver
License: MIT
Keywords: jce,tars
Platform: UNKNOWN
Classifier: Operating System :: OS Independent
Classifier: License :: OSI Approved :: MIT License
Classifier: Programming Language :: Python
Classifier: Programming Language :: Python :: 3.8
Classifier: Programming Language :: Python :: 3.9
Classifier: Programming Language :: Python :: Implementation :: CPython
Requires-Python: >=3.8
Requires-Dist: pydantic
